{ "backgroundcolor":"#000000",
 "height":22,
 "layers":[
        {
         "compression":"zlib",
         "data":"eJx7wsDA8GQU0wyvA2JJIjCx6sjRs26YubOPCEysOnL0jLpz1J2j7hx1J7o7FYjA5LqTWLOHU3iOunPUnaPuHDnuHArtz1FMGQYAOL9BmQ==",
         "encoding":"base64",
         "height":22,
         "name":"back",
         "opacity":0.5,
         "type":"tilelayer",
         "visible":true,
         "width":42,
         "x":0,
         "y":0
        }, 
        {
         "compression":"zlib",
         "data":"eJztzsEJAAAIxLDbf00XcQgRFFLoP4k2qyNzcnJycnJemJOTk\/ObU7MamzYeyw==",
         "encoding":"base64",
         "height":22,
         "name":"front",
         "opacity":1,
         "type":"tilelayer",
         "visible":true,
         "width":42,
         "x":0,
         "y":0
        }, 
        {
         "color":"#5555ff",
         "draworder":"topdown",
         "height":0,
         "name":"mods",
         "objects":[],
         "opacity":1,
         "type":"objectgroup",
         "visible":true,
         "width":0,
         "x":0,
         "y":0
        }, 
        {
         "color":"#ff0000",
         "draworder":"topdown",
         "height":0,
         "name":"objects",
         "objects":[
                {
                 "gid":5160,
                 "height":48,
                 "id":843,
                 "name":"",
                 "properties":
                    {

                    },
                 "rotation":0,
                 "type":"",
                 "visible":true,
                 "width":120,
                 "x":184,
                 "y":160
                }, 
                {
                 "gid":5160,
                 "height":48,
                 "id":844,
                 "name":"",
                 "properties":
                    {

                    },
                 "rotation":0,
                 "type":"",
                 "visible":true,
                 "width":120,
                 "x":64,
                 "y":160
                }, 
                {
                 "gid":5196,
                 "height":24,
                 "id":847,
                 "name":"",
                 "properties":
                    {

                    },
                 "rotation":0,
                 "type":"",
                 "visible":true,
                 "width":40,
                 "x":264,
                 "y":64
                }, 
                {
                 "gid":5196,
                 "height":24,
                 "id":848,
                 "name":"",
                 "properties":
                    {

                    },
                 "rotation":0,
                 "type":"",
                 "visible":true,
                 "width":40,
                 "x":224,
                 "y":64
                }, 
                {
                 "gid":5196,
                 "height":24,
                 "id":849,
                 "name":"",
                 "properties":
                    {

                    },
                 "rotation":0,
                 "type":"",
                 "visible":true,
                 "width":40,
                 "x":184,
                 "y":64
                }, 
                {
                 "gid":5196,
                 "height":24,
                 "id":850,
                 "name":"",
                 "properties":
                    {

                    },
                 "rotation":0,
                 "type":"",
                 "visible":true,
                 "width":40,
                 "x":144,
                 "y":64
                }, 
                {
                 "gid":5196,
                 "height":24,
                 "id":851,
                 "name":"",
                 "properties":
                    {

                    },
                 "rotation":0,
                 "type":"",
                 "visible":true,
                 "width":40,
                 "x":104,
                 "y":64
                }, 
                {
                 "gid":5196,
                 "height":24,
                 "id":852,
                 "name":"",
                 "properties":
                    {

                    },
                 "rotation":0,
                 "type":"",
                 "visible":true,
                 "width":40,
                 "x":64,
                 "y":64
                }, 
                {
                 "gid":5196,
                 "height":24,
                 "id":853,
                 "name":"",
                 "properties":
                    {

                    },
                 "rotation":0,
                 "type":"",
                 "visible":true,
                 "width":40,
                 "x":64,
                 "y":40
                }, 
                {
                 "gid":5196,
                 "height":24,
                 "id":854,
                 "name":"",
                 "properties":
                    {

                    },
                 "rotation":0,
                 "type":"",
                 "visible":true,
                 "width":40,
                 "x":104,
                 "y":40
                }, 
                {
                 "gid":5196,
                 "height":24,
                 "id":855,
                 "name":"",
                 "properties":
                    {

                    },
                 "rotation":0,
                 "type":"",
                 "visible":true,
                 "width":40,
                 "x":144,
                 "y":40
                }, 
                {
                 "gid":5196,
                 "height":24,
                 "id":856,
                 "name":"",
                 "properties":
                    {

                    },
                 "rotation":0,
                 "type":"",
                 "visible":true,
                 "width":40,
                 "x":184,
                 "y":40
                }, 
                {
                 "gid":5196,
                 "height":24,
                 "id":857,
                 "name":"",
                 "properties":
                    {

                    },
                 "rotation":0,
                 "type":"",
                 "visible":true,
                 "width":40,
                 "x":224,
                 "y":40
                }, 
                {
                 "gid":5196,
                 "height":24,
                 "id":858,
                 "name":"",
                 "properties":
                    {

                    },
                 "rotation":0,
                 "type":"",
                 "visible":true,
                 "width":40,
                 "x":264,
                 "y":40
                }, 
                {
                 "gid":5236,
                 "height":48,
                 "id":861,
                 "name":"",
                 "properties":
                    {

                    },
                 "rotation":0,
                 "type":"",
                 "visible":true,
                 "width":120,
                 "x":184,
                 "y":112
                }, 
                {
                 "gid":5236,
                 "height":48,
                 "id":862,
                 "name":"",
                 "properties":
                    {

                    },
                 "rotation":0,
                 "type":"",
                 "visible":true,
                 "width":120,
                 "x":64,
                 "y":112
                }, 
                {
                 "gid":5225,
                 "height":24,
                 "id":863,
                 "name":"",
                 "properties":
                    {

                    },
                 "rotation":0,
                 "type":"",
                 "visible":true,
                 "width":32,
                 "x":32,
                 "y":160
                }, 
                {
                 "gid":5225,
                 "height":24,
                 "id":864,
                 "name":"",
                 "properties":
                    {

                    },
                 "rotation":0,
                 "type":"",
                 "visible":true,
                 "width":32,
                 "x":32,
                 "y":136
                }, 
                {
                 "gid":5225,
                 "height":24,
                 "id":865,
                 "name":"",
                 "properties":
                    {

                    },
                 "rotation":0,
                 "type":"",
                 "visible":true,
                 "width":32,
                 "x":32,
                 "y":112
                }, 
                {
                 "gid":5225,
                 "height":24,
                 "id":866,
                 "name":"",
                 "properties":
                    {

                    },
                 "rotation":0,
                 "type":"",
                 "visible":true,
                 "width":32,
                 "x":32,
                 "y":88
                }, 
                {
                 "gid":5225,
                 "height":24,
                 "id":867,
                 "name":"",
                 "properties":
                    {

                    },
                 "rotation":0,
                 "type":"",
                 "visible":true,
                 "width":32,
                 "x":32,
                 "y":64
                }, 
                {
                 "gid":5225,
                 "height":24,
                 "id":868,
                 "name":"",
                 "properties":
                    {

                    },
                 "rotation":0,
                 "type":"",
                 "visible":true,
                 "width":32,
                 "x":32,
                 "y":40
                }],
         "opacity":1,
         "type":"objectgroup",
         "visible":true,
         "width":0,
         "x":0,
         "y":0
        }, 
        {
         "color":"#ffff00",
         "draworder":"topdown",
         "height":0,
         "name":"wiring - lights & guns",
         "objects":[],
         "opacity":1,
         "type":"objectgroup",
         "visible":true,
         "width":0,
         "x":0,
         "y":0
        }, 
        {
         "color":"#ff0000",
         "draworder":"topdown",
         "height":0,
         "name":"monsters & npcs",
         "objects":[],
         "opacity":1,
         "type":"objectgroup",
         "visible":true,
         "width":0,
         "x":0,
         "y":0
        }, 
        {
         "color":"#00ffff",
         "draworder":"topdown",
         "height":0,
         "name":"wiring - locked door",
         "objects":[],
         "opacity":1,
         "type":"objectgroup",
         "visible":true,
         "width":0,
         "x":0,
         "y":0
        }, 
        {
         "draworder":"topdown",
         "height":0,
         "name":"outside the map",
         "objects":[],
         "opacity":1,
         "type":"objectgroup",
         "visible":true,
         "width":0,
         "x":0,
         "y":0
        }, 
        {
         "draworder":"topdown",
         "height":0,
         "name":"anchors etc",
         "objects":[
                {
                 "gid":239,
                 "height":8,
                 "id":756,
                 "name":"",
                 "properties":
                    {

                    },
                 "rotation":0,
                 "type":"",
                 "visible":true,
                 "width":8,
                 "x":304,
                 "y":160
                }],
         "opacity":1,
         "type":"objectgroup",
         "visible":true,
         "width":0,
         "x":0,
         "y":0
        }, 
        {
         "draworder":"topdown",
         "height":0,
         "name":"items",
         "objects":[],
         "opacity":1,
         "type":"objectgroup",
         "visible":true,
         "width":0,
         "x":0,
         "y":0
        }],
 "nextobjectid":869,
 "orientation":"orthogonal",
 "properties":
    {

    },
 "renderorder":"right-down",
 "tileheight":8,
 "tilesets":[
        {
         "firstgid":1,
         "source":"..\/..\/..\/tilesets\/packed\/materials.json"
        }, 
        {
         "firstgid":191,
         "source":"..\/..\/..\/tilesets\/packed\/supports.json"
        }, 
        {
         "firstgid":227,
         "source":"..\/..\/..\/tilesets\/packed\/miscellaneous.json"
        }, 
        {
         "firstgid":247,
         "source":"..\/..\/..\/tilesets\/packed\/liquids.json"
        }, 
        {
         "firstgid":275,
         "source":"..\/..\/..\/tilesets\/packed\/objects-by-race\/generic.json"
        }, 
        {
         "firstgid":2040,
         "source":"..\/..\/..\/tilesets\/packed\/objects-by-race\/hylotl.json"
        }, 
        {
         "firstgid":2271,
         "source":"..\/..\/..\/tilesets\/packed\/objects-by-colonytag\/hylotl.json"
        }, 
        {
         "firstgid":2490,
         "source":"..\/..\/..\/tilesets\/packed\/objects-by-category\/breakable.json"
        }, 
        {
         "firstgid":2788,
         "source":"..\/..\/..\/tilesets\/packed\/objects-by-category\/crafting.json"
        }, 
        {
         "firstgid":2864,
         "source":"..\/..\/..\/tilesets\/packed\/objects-by-category\/decorative.json"
        }, 
        {
         "firstgid":4165,
         "source":"..\/..\/..\/tilesets\/packed\/objects-by-category\/door.json"
        }, 
        {
         "firstgid":4281,
         "source":"..\/..\/..\/tilesets\/packed\/objects-by-category\/light.json"
        }, 
        {
         "firstgid":4698,
         "source":"..\/..\/..\/tilesets\/packed\/objects-by-category\/pot.json"
        }, 
        {
         "firstgid":4995,
         "source":"..\/..\/..\/tilesets\/packed\/objects-by-category\/railpoint.json"
        }, 
        {
         "firstgid":4999,
         "source":"..\/..\/..\/tilesets\/packed\/objects-by-category\/seed.json"
        }, 
        {
         "firstgid":5075,
         "source":"..\/..\/..\/tilesets\/packed\/objects-by-category\/storage.json"
        }, 
        {
         "firstgid":5293,
         "source":"..\/..\/..\/tilesets\/packed\/objects-by-category\/teleportmarker.json"
        }, 
        {
         "firstgid":5307,
         "source":"..\/..\/..\/tilesets\/packed\/objects-by-category\/trap.json"
        }, 
        {
         "firstgid":5511,
         "source":"..\/..\/..\/tilesets\/packed\/objects-by-category\/wire.json"
        }],
 "tilewidth":8,
 "version":1,
 "width":42
}